extdict/__init__.py
extdict/table.py
extdict-1.0.0.dist-info/LICENSE
extdict-1.0.0.dist-info/METADATA
extdict-1.0.0.dist-info/WHEEL
extdict-1.0.0.dist-info/top_level.txt
extdict-1.0.0.dist-info/RECORD
