Metadata-Version: 2.1
Name: extdict
Version: 1.0.0
Summary: A Python package for managing tables with content, read-only indices, and size constraints.
Home-page: https://github.com/RinkyDinkyNooble/extdict
Author: RinkyDinkyNooble
License: MIT
Classifier: License :: OSI Approved :: MIT License
Classifier: Programming Language :: Python :: 3.13
Classifier: Operating System :: OS Independent
Classifier: Natural Language :: English
Classifier: Topic :: Utilities
Requires-Python: >=3.13.1
License-File: LICENSE
Provides-Extra: dev
Requires-Dist: pytest>=8.3.4; extra == "dev"
Requires-Dist: setuptools>=75.6.0; extra == "dev"
Requires-Dist: wheel>=0.45.1; extra == "dev"
Requires-Dist: twine>=6.0.1; extra == "dev"
